fdmep/__init__.py
fdmep/cli.py
fdmep/scaffolder.py
fdmep-0.2.0.dist-info/licenses/LICENSE
fdmep-0.2.0.dist-info/METADATA
fdmep-0.2.0.dist-info/WHEEL
fdmep-0.2.0.dist-info/entry_points.txt
fdmep-0.2.0.dist-info/top_level.txt
fdmep-0.2.0.dist-info/RECORD
