Metadata-Version: 2.4
Name: fdmep
Version: 0.2.0
Summary: CLI para inicialização rápida de extensões pyRevit
Author-email: Tiago Lima <tiagolima.r3@outlook.com>
License: MIT
Project-URL: Homepage, https://github.com/tiagolimar/fdmep-cli
Project-URL: Issues, https://github.com/tiagolimar/fdmep-cli/issues
Requires-Python: >=3.9
License-File: LICENSE
Requires-Dist: colorama>=0.4.6
Dynamic: license-file
